src/__init__.py
src/artifacts.py
src/bootconfig.py
src/install.py
src/versionmap.py
src/config/sclera.conf
scleradmin-1.0b3.dist-info/LICENSE
scleradmin-1.0b3.dist-info/METADATA
scleradmin-1.0b3.dist-info/NOTICE.txt
scleradmin-1.0b3.dist-info/WHEEL
scleradmin-1.0b3.dist-info/entry_points.txt
scleradmin-1.0b3.dist-info/top_level.txt
scleradmin-1.0b3.dist-info/RECORD
