Metadata-Version: 2.1
Name: scleradmin
Version: 1.0b3
Summary: Sclera Platform Administration Tool
Home-page: https://github.com/scleradb/scleradmin
Author: Sclera, Inc.
Author-email: dev@scleradb.com
License: UNKNOWN
Keywords: scleradb sclera virtualization admin installer
Platform: UNKNOWN
Classifier: Programming Language :: Python :: 3.8
Classifier: Programming Language :: Java
Classifier: License :: OSI Approved :: Apache Software License
Classifier: Operating System :: OS Independent
Classifier: Development Status :: 4 - Beta
Classifier: Environment :: Console
Classifier: Intended Audience :: Developers
Classifier: Intended Audience :: Information Technology
Classifier: Topic :: System :: Installation/Setup
Requires-Python: >=3.8
Requires-Dist: requests
